calabrio_py/__init__.py
calabrio_py/api.py
calabrio_py/manager.py
calabrio_py-0.1.31.dist-info/METADATA
calabrio_py-0.1.31.dist-info/WHEEL
calabrio_py-0.1.31.dist-info/top_level.txt
calabrio_py-0.1.31.dist-info/RECORD
