Metadata-Version: 2.1
Name: calabrio-py
Version: 0.1.31
Summary: A Python client library for accessing the Calabrio API.
Author: yachimat
Author-email: podman1220@hotmail.com
Requires-Dist: requests >=2.28.1
Requires-Dist: aiohttp >=3.8.3
Requires-Dist: python-dateutil >=2.8.2
